emby_exporter/__init__.py
emby_exporter/emby_exporter.py
emby_exporter-0.1.4.dist-info/LICENSE
emby_exporter-0.1.4.dist-info/METADATA
emby_exporter-0.1.4.dist-info/WHEEL
emby_exporter-0.1.4.dist-info/entry_points.txt
emby_exporter-0.1.4.dist-info/top_level.txt
emby_exporter-0.1.4.dist-info/RECORD
