Metadata-Version: 2.1
Name: emby-exporter
Version: 0.1.4
Summary: Export emby metrics for prometheus
Home-page: https://github.com/dr1s/emby_exporter.py
Author: dr1s
License: MIT
Platform: UNKNOWN
Requires-Dist: prometheus-client
Requires-Dist: embypy
